{
    "frames": [
        {
            "frame": {
                "x": 79,
                "y": 22,
                "w": 59,
                "h": 27
            }
        },
        {
            "frame": {
                "x": 0,
                "y": 20,
                "w": 58,
                "h": 29
            }
        },
        {
            "frame": {
                "x": 58,
                "y": 0,
                "w": 21,
                "h": 19
            }
        },
        {
            "frame": {
                "x": 58,
                "y": 19,
                "w": 21,
                "h": 33
            }
        },
        {
            "frame": {
                "x": 52,
                "y": 53,
                "w": 34,
                "h": 21
            }
        }
    ],
    "meta": {
        "FrameCount": 5
    }
}